<?xml version="1.0" encoding="utf-8" ?><dwsync><file name="banknote.png" server="disruptivedesign.ca" local="3451776488" remote="7796393476" Dst="-1" /><file name="bulb.png" server="disruptivedesign.ca" local="3451776488" remote="-4611698487510989308" Dst="-1" /><file name="bubble.png" server="disruptivedesign.ca" local="3451776488" remote="-4611698487510989308" Dst="-1" /><file name="calendar.png" server="disruptivedesign.ca" local="3451776488" remote="-4611698487510989308" Dst="-1" /><file name="clip.png" server="disruptivedesign.ca" local="3451776488" remote="-4611698487510989308" Dst="-1" /><file name="camera.png" server="disruptivedesign.ca" local="3451776488" remote="-4611698487510989308" Dst="-1" /><file name="clock.png" server="disruptivedesign.ca" local="3451776488" remote="-4611698487510989308" Dst="-1" /><file name="cloud.png" server="disruptivedesign.ca" local="3451776488" remote="-4611698487510989308" Dst="-1" /><file name="crowd.png" server="disruptivedesign.ca" local="3468962477" remote="-4611698487510989308" Dst="-1" /><file name="cup.png" server="disruptivedesign.ca" local="3451776488" remote="-4611698487510989308" Dst="-1" /><file name="diamond.png" server="disruptivedesign.ca" local="3451776488" remote="-4611698487510989308" Dst="-1" /><file name="data.png" server="disruptivedesign.ca" local="3451776488" remote="-4611698487510989308" Dst="-1" /><file name="display.png" server="disruptivedesign.ca" local="3451776488" remote="-4611698487510989308" Dst="-1" /><file name="fire.png" server="disruptivedesign.ca" local="3451776488" remote="-4611698487510989308" Dst="-1" /><file name="eye.png" server="disruptivedesign.ca" local="3451776488" remote="-4611698487510989308" Dst="-1" /><file name="food.png" server="disruptivedesign.ca" local="3451776488" remote="-4611698487510989308" Dst="-1" /><file name="key.png" server="disruptivedesign.ca" local="3451776488" remote="-4611698487510989308" Dst="-1" /><file name="heart.png" server="disruptivedesign.ca" local="3451776488" remote="-4611698487510989308" Dst="-1" /><file name="lab.png" server="disruptivedesign.ca" local="3451776488" remote="-4611698487510989308" Dst="-1" /><file name="leaf.png" server="disruptivedesign.ca" local="3468960368" remote="-4611698487510989308" Dst="-1" /><file name="like.png" server="disruptivedesign.ca" local="3451776488" remote="-4611698487510989308" Dst="-1" /><file name="location.png" server="disruptivedesign.ca" local="3451776488" remote="-4611698487510989308" Dst="-1" /><file name="mail.png" server="disruptivedesign.ca" local="3451776488" remote="-4611698487510989308" Dst="-1" /><file name="lock.png" server="disruptivedesign.ca" local="3451776488" remote="-4611698487510989308" Dst="-1" /><file name="megaphone.png" server="disruptivedesign.ca" local="3451776488" remote="-4611698487510989308" Dst="-1" /><file name="news.png" server="disruptivedesign.ca" local="3451776488" remote="-4611698487510989308" Dst="-1" /><file name="music.png" server="disruptivedesign.ca" local="3451776488" remote="-4611698487510989308" Dst="-1" /><file name="note.png" server="disruptivedesign.ca" local="3451776488" remote="-4611698487510989308" Dst="-1" /><file name="params.png" server="disruptivedesign.ca" local="3451776488" remote="-4611698487510989308" Dst="-1" /><file name="paperplane.png" server="disruptivedesign.ca" local="3451776488" remote="-4611698487510989308" Dst="-1" /><file name="pen.png" server="disruptivedesign.ca" local="3451776488" remote="-4611698487510989308" Dst="-1" /><file name="photo.png" server="disruptivedesign.ca" local="3451776488" remote="-4611698487510989308" Dst="-1" /><file name="phone.png" server="disruptivedesign.ca" local="3451776488" remote="-4611698487510989308" Dst="-1" /><file name="search.png" server="disruptivedesign.ca" local="3451776488" remote="-4611698487510989308" Dst="-1" /><file name="shop.png" server="disruptivedesign.ca" local="3451776488" remote="-4611698487510989308" Dst="-1" /><file name="settings.png" server="disruptivedesign.ca" local="3451776488" remote="-4611698487510989308" Dst="-1" /><file name="sound.png" server="disruptivedesign.ca" local="3451776488" remote="-4611698487510989308" Dst="-1" /><file name="star.png" server="disruptivedesign.ca" local="3451776488" remote="-4611698487510989308" Dst="-1" /><file name="stack.png" server="disruptivedesign.ca" local="3451776488" remote="-4611698487510989308" Dst="-1" /><file name="study.png" server="disruptivedesign.ca" local="3451776488" remote="-4611698487510989308" Dst="-1" /><file name="tag.png" server="disruptivedesign.ca" local="3451776488" remote="-4611698487510989308" Dst="-1" /><file name="t-shirt.png" server="disruptivedesign.ca" local="3451776488" remote="-4611698487510989308" Dst="-1" /><file name="Thumbs.db" server="disruptivedesign.ca" local="3451776522" remote="-4611698487510989248" Dst="-1" /><file name="trash.png" server="disruptivedesign.ca" local="3451776488" remote="-4611698487510989248" Dst="-1" /><file name="truck.png" server="disruptivedesign.ca" local="3451776488" remote="-4611698487510989248" Dst="-1" /><file name="user.png" server="disruptivedesign.ca" local="3451776488" remote="-4611698487510989248" Dst="-1" /><file name="tv.png" server="disruptivedesign.ca" local="3451776488" remote="-4611698487510989248" Dst="-1" /><file name="video.png" server="disruptivedesign.ca" local="3451776488" remote="-4611698487510989248" Dst="-1" /><file name="wallet.png" server="disruptivedesign.ca" local="3451776488" remote="-4611698487510989248" Dst="-1" /><file name="world.png" server="disruptivedesign.ca" local="3451776488" remote="7796393536" Dst="-1" /><file name="vynil.png" server="disruptivedesign.ca" local="3451776488" remote="-4611698487510989248" Dst="-1" /><file name="rocket.png" server="disruptivedesign.ca" local="3469478203" remote="-4611698487510989308" Dst="-1" /><file name="banknote.png" server="disruptivedesign.ca//public_html/" local="3451776488" remote="7796396356" Dst="-1" /><file name="bubble.png" server="disruptivedesign.ca//public_html/" local="3451776488" remote="-4611698487510986428" Dst="-1" /><file name="camera.png" server="disruptivedesign.ca//public_html/" local="3451776488" remote="-4611698487510986428" Dst="-1" /><file name="bulb.png" server="disruptivedesign.ca//public_html/" local="3451776488" remote="-4611698487510986428" Dst="-1" /><file name="calendar.png" server="disruptivedesign.ca//public_html/" local="3451776488" remote="-4611698487510986428" Dst="-1" /><file name="clip.png" server="disruptivedesign.ca//public_html/" local="3451776488" remote="-4611698487510986428" Dst="-1" /><file name="clock.png" server="disruptivedesign.ca//public_html/" local="3451776488" remote="-4611698487510986428" Dst="-1" /><file name="cloud.png" server="disruptivedesign.ca//public_html/" local="3451776488" remote="-4611698487510986428" Dst="-1" /><file name="crowd.png" server="disruptivedesign.ca//public_html/" local="3468962477" remote="-4611698487510986428" Dst="-1" /><file name="cup.png" server="disruptivedesign.ca//public_html/" local="3451776488" remote="-4611698487510986428" Dst="-1" /><file name="data.png" server="disruptivedesign.ca//public_html/" local="3451776488" remote="-4611698487510986428" Dst="-1" /><file name="diamond.png" server="disruptivedesign.ca//public_html/" local="3451776488" remote="-4611698487510986428" Dst="-1" /><file name="display.png" server="disruptivedesign.ca//public_html/" local="3451776488" remote="-4611698487510986428" Dst="-1" /><file name="eye.png" server="disruptivedesign.ca//public_html/" local="3451776488" remote="-4611698487510986428" Dst="-1" /><file name="fire.png" server="disruptivedesign.ca//public_html/" local="3451776488" remote="-4611698487510986428" Dst="-1" /><file name="food.png" server="disruptivedesign.ca//public_html/" local="3451776488" remote="-4611698487510986428" Dst="-1" /><file name="heart.png" server="disruptivedesign.ca//public_html/" local="3451776488" remote="-4611698487510986428" Dst="-1" /><file name="key.png" server="disruptivedesign.ca//public_html/" local="3451776488" remote="-4611698487510986428" Dst="-1" /><file name="lab.png" server="disruptivedesign.ca//public_html/" local="3451776488" remote="-4611698487510986428" Dst="-1" /><file name="leaf.png" server="disruptivedesign.ca//public_html/" local="3468960368" remote="-4611698487510986428" Dst="-1" /><file name="like.png" server="disruptivedesign.ca//public_html/" local="3451776488" remote="-4611698487510986428" Dst="-1" /><file name="location.png" server="disruptivedesign.ca//public_html/" local="3451776488" remote="-4611698487510986428" Dst="-1" /><file name="lock.png" server="disruptivedesign.ca//public_html/" local="3451776488" remote="-4611698487510986428" Dst="-1" /><file name="mail.png" server="disruptivedesign.ca//public_html/" local="3451776488" remote="-4611698487510986428" Dst="-1" /><file name="megaphone.png" server="disruptivedesign.ca//public_html/" local="3451776488" remote="-4611698487510986428" Dst="-1" /><file name="music.png" server="disruptivedesign.ca//public_html/" local="3451776488" remote="-4611698487510986428" Dst="-1" /><file name="news.png" server="disruptivedesign.ca//public_html/" local="3451776488" remote="-4611698487510986428" Dst="-1" /><file name="note.png" server="disruptivedesign.ca//public_html/" local="3451776488" remote="-4611698487510986428" Dst="-1" /><file name="paperplane.png" server="disruptivedesign.ca//public_html/" local="3451776488" remote="-4611698487510986428" Dst="-1" /><file name="params.png" server="disruptivedesign.ca//public_html/" local="3451776488" remote="-4611698487510986428" Dst="-1" /><file name="pen.png" server="disruptivedesign.ca//public_html/" local="3451776488" remote="-4611698487510986428" Dst="-1" /><file name="phone.png" server="disruptivedesign.ca//public_html/" local="3451776488" remote="-4611698487510986428" Dst="-1" /><file name="photo.png" server="disruptivedesign.ca//public_html/" local="3451776488" remote="-4611698487510986428" Dst="-1" /><file name="rocket.png" server="disruptivedesign.ca//public_html/" local="3469478203" remote="-4611698487510986428" Dst="-1" /><file name="search.png" server="disruptivedesign.ca//public_html/" local="3451776488" remote="-4611698487510986428" Dst="-1" /><file name="settings.png" server="disruptivedesign.ca//public_html/" local="3451776488" remote="-4611698487510986428" Dst="-1" /><file name="shop.png" server="disruptivedesign.ca//public_html/" local="3451776488" remote="-4611698487510986428" Dst="-1" /><file name="sound.png" server="disruptivedesign.ca//public_html/" local="3451776488" remote="-4611698487510986428" Dst="-1" /><file name="stack.png" server="disruptivedesign.ca//public_html/" local="3451776488" remote="-4611698487510986428" Dst="-1" /><file name="star.png" server="disruptivedesign.ca//public_html/" local="3451776488" remote="-4611698487510986428" Dst="-1" /><file name="study.png" server="disruptivedesign.ca//public_html/" local="3451776488" remote="-4611698487510986428" Dst="-1" /><file name="t-shirt.png" server="disruptivedesign.ca//public_html/" local="3451776488" remote="-4611698487510986428" Dst="-1" /><file name="tag.png" server="disruptivedesign.ca//public_html/" local="3451776488" remote="-4611698487510986428" Dst="-1" /><file name="trash.png" server="disruptivedesign.ca//public_html/" local="3451776488" remote="-4611698487510986428" Dst="-1" /><file name="truck.png" server="disruptivedesign.ca//public_html/" local="3451776488" remote="-4611698487510986428" Dst="-1" /><file name="Thumbs.db" server="disruptivedesign.ca//public_html/" local="3451776522" remote="-4611698487510986428" Dst="-1" /><file name="tv.png" server="disruptivedesign.ca//public_html/" local="3451776488" remote="-4611698487510986428" Dst="-1" /><file name="user.png" server="disruptivedesign.ca//public_html/" local="3451776488" remote="-4611698487510986428" Dst="-1" /><file name="video.png" server="disruptivedesign.ca//public_html/" local="3451776488" remote="-4611698487510986428" Dst="-1" /><file name="vynil.png" server="disruptivedesign.ca//public_html/" local="3451776488" remote="-4611698487510986428" Dst="-1" /><file name="wallet.png" server="disruptivedesign.ca//public_html/" local="3451776488" remote="-4611698487510986428" Dst="-1" /><file name="world.png" server="disruptivedesign.ca//public_html/" local="3451776488" remote="-4611698487510986368" Dst="-1" /></dwsync>